[{"progrnumber": "1", "actual_stop_id": "7391", "stop_lat": "53.33909075", "stop_lon": "-6.249916017", "stop_id": "8220DB007391", "stop_name": "Merrion Square South"}, {"progrnumber": "2", "actual_stop_id": "493", "stop_lat": "53.33985342", "stop_lon": "-6.247376823", "stop_id": "8220DB000493", "stop_name": "Merrion Square, Holles Street"}, {"progrnumber": "3", "actual_stop_id": "494", "stop_lat": "53.34133589", "stop_lon": "-6.251626258", "stop_id": "8220DB000494", "stop_name": "Clare Street"}, {"progrnumber": "4", "actual_stop_id": "495", "stop_lat": "53.34359132", "stop_lon": "-6.249746705", "stop_id": "8220DB000495", "stop_name": "Pearse Station, Outside Train Station"}, {"progrnumber": "5", "actual_stop_id": "400", "stop_lat": "53.34475116", "stop_lon": "-6.252838258", "stop_id": "8220DB000400", "stop_name": "Trinity College, Shaw Street"}, {"progrnumber": "6", "actual_stop_id": "346", "stop_lat": "53.34550627", "stop_lon": "-6.256532266000001", "stop_id": "8220DB000346", "stop_name": "Trinity College, Garda Station"}, {"progrnumber": "7", "actual_stop_id": "317", "stop_lat": "53.34624485", "stop_lon": "-6.25910058", "stop_id": "8220DB000317", "stop_name": "Dublin City South, Westmoreland Street"}, {"progrnumber": "8", "actual_stop_id": "312", "stop_lat": "53.34547647", "stop_lon": "-6.266206155", "stop_id": "8220DB000312", "stop_name": "Temple Bar, Wellington Quay"}, {"progrnumber": "9", "actual_stop_id": "1444", "stop_lat": "53.34511841", "stop_lon": "-6.273745471", "stop_id": "8220DB001444", "stop_name": "Dublin City South, Merchant's Quay"}, {"progrnumber": "10", "actual_stop_id": "1445", "stop_lat": "53.34567841", "stop_lon": "-6.27828884", "stop_id": "8220DB001445", "stop_name": "James's Gate, Ushers Quay"}, {"progrnumber": "11", "actual_stop_id": "7078", "stop_lat": "53.34791031", "stop_lon": "-6.2928739039999995", "stop_id": "8220DB007078", "stop_name": "Phoenix Park, Sean Heuston Bridge"}, {"progrnumber": "12", "actual_stop_id": "1449", "stop_lat": "53.34815283", "stop_lon": "-6.297896095", "stop_id": "8220DB001449", "stop_name": "Phoenix Park, Conyngham Road Bus Garage"}, {"progrnumber": "13", "actual_stop_id": "1450", "stop_lat": "53.3481554", "stop_lon": "-6.301861412999999", "stop_id": "8220DB001450", "stop_name": "Phoenix Park, Wellington Monument"}, {"progrnumber": "14", "actual_stop_id": "1451", "stop_lat": "53.34827828", "stop_lon": "-6.305446445", "stop_id": "8220DB001451", "stop_name": "Islandbridge, Bridgewater Business Centre"}, {"progrnumber": "15", "actual_stop_id": "2191", "stop_lat": "53.34802557", "stop_lon": "-6.310443265", "stop_id": "8220DB002191", "stop_name": "Islandbridge, Sarah Place"}, {"progrnumber": "16", "actual_stop_id": "2192", "stop_lat": "53.34724562", "stop_lon": "-6.315671093", "stop_id": "8220DB002192", "stop_name": "Islandbridge, U.C.D Boat Club"}, {"progrnumber": "17", "actual_stop_id": "2193", "stop_lat": "53.34638455", "stop_lon": "-6.323455291", "stop_id": "8220DB002193", "stop_name": "Islandbridge, Garda Boat Club"}, {"progrnumber": "18", "actual_stop_id": "2194", "stop_lat": "53.34619334", "stop_lon": "-6.328404302999999", "stop_id": "8220DB002194", "stop_name": "Islandbridge, Sports Grounds"}, {"progrnumber": "19", "actual_stop_id": "2195", "stop_lat": "53.34674411", "stop_lon": "-6.337589993", "stop_id": "8220DB002195", "stop_name": "Chapelizod, Chapelizod School"}, {"progrnumber": "20", "actual_stop_id": "2196", "stop_lat": "53.34783463", "stop_lon": "-6.341678151", "stop_id": "8220DB002196", "stop_name": "Chapelizod, Kings Hall"}, {"progrnumber": "21", "actual_stop_id": "2197", "stop_lat": "53.34816555", "stop_lon": "-6.346742215", "stop_id": "8220DB002197", "stop_name": "Lucan Road (Chapelizod Hill Rd)"}, {"progrnumber": "22", "actual_stop_id": "2198", "stop_lat": "53.35062514", "stop_lon": "-6.351063289", "stop_id": "8220DB002198", "stop_name": "Chapelizod, Lucan Road (Belgrove Park)"}, {"progrnumber": "23", "actual_stop_id": "2200", "stop_lat": "53.35028275", "stop_lon": "-6.3529541510000005", "stop_id": "8220DB002200", "stop_name": "Chapelizod, Chapelizod By Pass Bridge"}, {"progrnumber": "24", "actual_stop_id": "2201", "stop_lat": "53.35327375", "stop_lon": "-6.364571165", "stop_id": "8230DB002201", "stop_name": "Palmerstown, Lucan Road (The Oval)"}, {"progrnumber": "25", "actual_stop_id": "7239", "stop_lat": "53.35406141", "stop_lon": "-6.368927567", "stop_id": "8230DB007239", "stop_name": "Palmerstown, Lucan Road N4"}, {"progrnumber": "26", "actual_stop_id": "4401", "stop_lat": "53.35475553", "stop_lon": "-6.371710305", "stop_id": "8230DB004401", "stop_name": "Palmerstown, Lucan Road"}, {"progrnumber": "27", "actual_stop_id": "2202", "stop_lat": "53.35438177", "stop_lon": "-6.373301923", "stop_id": "8230DB002202", "stop_name": "Palmerstown, Kennelsfort Road"}, {"progrnumber": "28", "actual_stop_id": "2203", "stop_lat": "53.35320727", "stop_lon": "-6.376155793", "stop_id": "8230DB002203", "stop_name": "Palmerstown, Upper Kennelsfort Road"}]