[{"progrnumber": "1", "actual_stop_id": "4533", "stop_lat": "53.16950516", "stop_lon": "-6.136486412000001", "stop_id": "8350DB004533", "stop_name": "Kilmacanogue (Esso Garage)"}, {"progrnumber": "2", "actual_stop_id": "4844", "stop_lat": "53.17437571", "stop_lon": "-6.139282279", "stop_id": "8350DB004844", "stop_name": "Glencree, Halting Site"}, {"progrnumber": "3", "actual_stop_id": "4177", "stop_lat": "53.18609984", "stop_lon": "-6.129152691", "stop_id": "8350DB004177", "stop_name": "Bray, Springfield Cemetery"}, {"progrnumber": "4", "actual_stop_id": "4178", "stop_lat": "53.18808628", "stop_lon": "-6.127435032", "stop_id": "8350DB004178", "stop_name": "Bray, Killarney Road (Glenthorn)"}, {"progrnumber": "10", "actual_stop_id": "4304", "stop_lat": "53.18930313", "stop_lon": "-6.102659234", "stop_id": "8350DB004304", "stop_name": "Bray, Newcourt Road"}, {"progrnumber": "11", "actual_stop_id": "4148", "stop_lat": "53.19178415", "stop_lon": "-6.104929303", "stop_id": "8350DB004148", "stop_name": "Bray, Putland Villas"}, {"progrnumber": "12", "actual_stop_id": "4149", "stop_lat": "53.19356328", "stop_lon": "-6.10658698", "stop_id": "8350DB004149", "stop_name": "Bray, Vevay Road #2"}, {"progrnumber": "13", "actual_stop_id": "3045", "stop_lat": "53.19743083", "stop_lon": "-6.109006005", "stop_id": "8350DB003045", "stop_name": "Bray, Vevay Road (Church Road)"}, {"progrnumber": "14", "actual_stop_id": "4150", "stop_lat": "53.20011663", "stop_lon": "-6.11059424", "stop_id": "8350DB004150", "stop_name": "Bray, Market House"}, {"progrnumber": "15", "actual_stop_id": "4151", "stop_lat": "53.20186865", "stop_lon": "-6.110547104", "stop_id": "8350DB004151", "stop_name": "Bray, Bray Town Hall"}, {"progrnumber": "16", "actual_stop_id": "2997", "stop_lat": "53.20312352", "stop_lon": "-6.109758356", "stop_id": "8350DB002997", "stop_name": "Bray, Main Street Bray (Florence Road)"}, {"progrnumber": "17", "actual_stop_id": "4156", "stop_lat": "53.20496738", "stop_lon": "-6.103614006", "stop_id": "8350DB004156", "stop_name": "Quinnsborough Road (Seymour Rd)"}, {"progrnumber": "19", "actual_stop_id": "4170", "stop_lat": "53.20348377", "stop_lon": "-6.106972992", "stop_id": "8350DB004170", "stop_name": "Bray, Methodist Church"}, {"progrnumber": "20", "actual_stop_id": "4153", "stop_lat": "53.20489065", "stop_lon": "-6.109530865", "stop_id": "8350DB004153", "stop_name": "Main Street (Quinnsborough Road)"}, {"progrnumber": "21", "actual_stop_id": "4154", "stop_lat": "53.20663408", "stop_lon": "-6.112343592", "stop_id": "8350DB004154", "stop_name": "Bray (Wicklow), Castle Street"}, {"progrnumber": "22", "actual_stop_id": "4416", "stop_lat": "53.20834387", "stop_lon": "-6.114738805", "stop_id": "8350DB004416", "stop_name": "Bray, Roseville Court"}, {"progrnumber": "23", "actual_stop_id": "4201", "stop_lat": "53.21112535", "stop_lon": "-6.117835856", "stop_id": "8350DB004201", "stop_name": "Bray, Greenhouse Garden Centre"}, {"progrnumber": "24", "actual_stop_id": "4202", "stop_lat": "53.21600035", "stop_lon": "-6.11974851", "stop_id": "8250DB004202", "stop_name": "D??n Laoghaire-Rathdown, Saint Brendan's College"}, {"progrnumber": "25", "actual_stop_id": "4203", "stop_lat": "53.2197606", "stop_lon": "-6.120512294", "stop_id": "8250DB004203", "stop_name": "D??n Laoghaire-Rathdown, Crinken Church"}, {"progrnumber": "26", "actual_stop_id": "5090", "stop_lat": "53.22170381", "stop_lon": "-6.121760115", "stop_id": "8250DB005090", "stop_name": "D??n Laoghaire-Rathdown, Shaganagh Cemetery"}, {"progrnumber": "27", "actual_stop_id": "4204", "stop_lat": "53.22332409", "stop_lon": "-6.12362126", "stop_id": "8250DB004204", "stop_name": "D??n Laoghaire-Rathdown, Shanganagh Castle"}, {"progrnumber": "28", "actual_stop_id": "4205", "stop_lat": "53.22453947", "stop_lon": "-6.124886148", "stop_id": "8250DB004205", "stop_name": "Shankill, Crinken Lodge"}, {"progrnumber": "29", "actual_stop_id": "4206", "stop_lat": "53.22750292", "stop_lon": "-6.124711709", "stop_id": "8250DB004206", "stop_name": "Shankill, Claremont Estate"}, {"progrnumber": "30", "actual_stop_id": "3140", "stop_lat": "53.22974308", "stop_lon": "-6.12426927", "stop_id": "8250DB003140", "stop_name": "Shankill, Dublin Road"}, {"progrnumber": "32", "actual_stop_id": "3552", "stop_lat": "53.23720289", "stop_lon": "-6.123089085", "stop_id": "8250DB003552", "stop_name": "Shankill, Rathsallagh Estate"}, {"progrnumber": "33", "actual_stop_id": "3553", "stop_lat": "53.23902653", "stop_lon": "-6.123024264", "stop_id": "8250DB003553", "stop_name": "Shankill, Hazelwood Estate"}, {"progrnumber": "34", "actual_stop_id": "3554", "stop_lat": "53.24289815", "stop_lon": "-6.1217310089999994", "stop_id": "8250DB003554", "stop_name": "Loughlinstown, Shanganagh Bridge"}, {"progrnumber": "35", "actual_stop_id": "3555", "stop_lat": "53.2449123", "stop_lon": "-6.121777647999999", "stop_id": "8250DB003555", "stop_name": "Loughlinstown, Shanganagh Road"}, {"progrnumber": "36", "actual_stop_id": "3556", "stop_lat": "53.24811797", "stop_lon": "-6.123285667999999", "stop_id": "8250DB003556", "stop_name": "Ballybrack, Liwara"}, {"progrnumber": "37", "actual_stop_id": "3557", "stop_lat": "53.24939627", "stop_lon": "-6.123409549", "stop_id": "8250DB003557", "stop_name": "Ballybrack, The Sycamores"}, {"progrnumber": "41", "actual_stop_id": "3225", "stop_lat": "53.25529487", "stop_lon": "-6.13385301", "stop_id": "8250DB003225", "stop_name": "Druid Valley, Churchview Rd,  Willow Vale"}, {"progrnumber": "42", "actual_stop_id": "3226", "stop_lat": "53.25854707", "stop_lon": "-6.137773557999999", "stop_id": "8250DB003226", "stop_name": "Ballybrack, Churchview Road (Granville Rd)"}, {"progrnumber": "43", "actual_stop_id": "3227", "stop_lat": "53.26195417", "stop_lon": "-6.137805394", "stop_id": "8250DB003227", "stop_name": "Sallynoggin, Churchview Road"}, {"progrnumber": "44", "actual_stop_id": "3228", "stop_lat": "53.26475425", "stop_lon": "-6.134655395", "stop_id": "8250DB003228", "stop_name": "Killiney, Churchview Road"}, {"progrnumber": "45", "actual_stop_id": "3229", "stop_lat": "53.26535278", "stop_lon": "-6.134419453", "stop_id": "8250DB003229", "stop_name": "Killiney, Church Road"}, {"progrnumber": "46", "actual_stop_id": "7472", "stop_lat": "53.26706808", "stop_lon": "-6.136623621", "stop_id": "8250DB007472", "stop_name": "Rochestown Avenue Opposite Killiney Shop"}, {"progrnumber": "47", "actual_stop_id": "3230", "stop_lat": "53.26850153", "stop_lon": "-6.139200038999999", "stop_id": "8250DB003230", "stop_name": "Sallynoggin, Drumkeen Manor"}, {"progrnumber": "48", "actual_stop_id": "3231", "stop_lat": "53.27008949", "stop_lon": "-6.141889872999999", "stop_id": "8250DB003231", "stop_name": "Sallynoggin, Granitefield Manor"}, {"progrnumber": "49", "actual_stop_id": "3246", "stop_lat": "53.27107628", "stop_lon": "-6.143496397000001", "stop_id": "8250DB003246", "stop_name": "Sallynoggin, Rochestown Avenue(Johnstown Road)"}, {"progrnumber": "50", "actual_stop_id": "3247", "stop_lat": "53.27264524", "stop_lon": "-6.146127392", "stop_id": "8250DB003247", "stop_name": "Sallynoggin, Sallynoggin Road"}, {"progrnumber": "51", "actual_stop_id": "7056", "stop_lat": "53.27353131", "stop_lon": "-6.147618505", "stop_id": "8250DB007056", "stop_name": "Sallynoggin, Somerton Estate"}, {"progrnumber": "54", "actual_stop_id": "3236", "stop_lat": "53.2779835", "stop_lon": "-6.140302725", "stop_id": "8250DB003236", "stop_name": "Sallynoggin, Sallynoggin Road (O'Donnell Gardens)"}, {"progrnumber": "55", "actual_stop_id": "3237", "stop_lat": "53.27914236", "stop_lon": "-6.137957911", "stop_id": "8250DB003237", "stop_name": "Glenageary, Sallynoggin Road"}, {"progrnumber": "56", "actual_stop_id": "3238", "stop_lat": "53.28330973", "stop_lon": "-6.133727199", "stop_id": "8250DB003238", "stop_name": "Glenageary, Holmstown Avenue"}, {"progrnumber": "57", "actual_stop_id": "3239", "stop_lat": "53.2843865", "stop_lon": "-6.133035331", "stop_id": "8250DB003239", "stop_name": "Glenageary, Lower Glenageary Rd (Crosthwaite Park Sth)"}, {"progrnumber": "58", "actual_stop_id": "3240", "stop_lat": "53.28717187", "stop_lon": "-6.131248929", "stop_id": "8250DB003240", "stop_name": "Lower Glenageary Road (Corrig Road)"}, {"progrnumber": "59", "actual_stop_id": "3068", "stop_lat": "53.28982949", "stop_lon": "-6.1304879020000005", "stop_id": "8250DB003068", "stop_name": "Dun Laoghaire, Upper George's Street"}, {"progrnumber": "60", "actual_stop_id": "3069", "stop_lat": "53.29075303", "stop_lon": "-6.132637683", "stop_id": "8250DB003069", "stop_name": "Dun Laoghaire, Upper George's Street"}, {"progrnumber": "61", "actual_stop_id": "3070", "stop_lat": "53.292115100000004", "stop_lon": "-6.135818533999999", "stop_id": "8250DB003070", "stop_name": "Dun Laoghaire, Dun Laoghaire Shopping Centre"}]